dulrs/__init__.py
dulrs/dulrs.py
dulrs/dulrs_test.py
dulrs-0.0.3.dist-info/METADATA
dulrs-0.0.3.dist-info/WHEEL
dulrs-0.0.3.dist-info/top_level.txt
dulrs-0.0.3.dist-info/RECORD
