Metadata-Version: 2.1
Name: dulrs
Version: 0.0.3
Summary: A Python package to generate heatmaps, lowrank, and sparsity from deep learning models.
Home-page: https://github.com/fengyiwu98
Author: Fengyi_Wu
Author-email: wufengyi98@163.com
Classifier: Programming Language :: Python :: 3
Classifier: License :: OSI Approved :: MIT License
Classifier: Operating System :: OS Independent
Requires-Python: >=3.7
Requires-Dist: torch
Requires-Dist: torchvision
Requires-Dist: numpy
Requires-Dist: scipy
Requires-Dist: opencv-python
Requires-Dist: matplotlib
Requires-Dist: pandas
Requires-Dist: plotnine
Requires-Dist: Pillow
Requires-Dist: statistics
